{
  "401859967": {
    "game_id": "401859967",
    "home_team": "Spurs",
    "away_team": "Knicks",
    "date": "2026-06-14T00:30Z",
    "status": "6/13 - 8:30 PM EDT",
    "home_picks": [
      {
        "prop": "AST",
        "label": "Devin Vassell plus de 2.5 passes",
        "line": 2.5,
        "direction": "over",
        "confidence": 65,
        "confidence_base": 73,
        "signal_bonus": 5,
        "signal_confirm": "🆚 OVER hit rate 3/4 vs NY",
        "signal_warning": "",
        "venue_hit": "5/9",
        "venue_hit_pct": 56,
        "h2h_hit": "3/4",
        "h2h_hit_pct": 75,
        "cote_min": 1.37,
        "real_cote": 2.18,
        "book": "fanduel",
        "books": [
          {
            "book": "fanduel",
            "cote": 2.18
          },
          {
            "book": "betmgm",
            "cote": 2.15
          },
          {
            "book": "draftkings",
            "cote": 2.12
          },
          {
            "book": "pinnacle",
            "cote": 2.07
          }
        ],
        "edge": 59.1,
        "is_real_line": true,
        "value": [
          "🎯",
          "Real DK/FD",
          "#22c55e"
        ],
        "hit_rate": "6/10",
        "hit_pct": 60,
        "hit_l10": "6/10",
        "hit_l10_pct": 60,
        "hit_l20": "13/20",
        "hit_l20_pct": 65,
        "trend": "stable",
        "trend_delta": -5.0,
        "trend_icon": "",
        "context": {
          "pace": 0.99,
          "def": 0.935,
          "def_rank": 26,
          "def_stat": "passes"
        },
        "def_argument": "Adversaire solide vs passes (#26/30)",
        "rotation_warning": null,
        "last_min_warning": null,
        "book_divergence_warning": null,
        "bounce_back": null,
        "is_series": true,
        "series_state": "down",
        "series_urgency": true,
        "h2h_avg": 3.0,
        "h2h_n": 4,
        "venue_avg": 2.9,
        "venue_n": 9,
        "venue": "domicile",
        "opp_abbr": "NY",
        "kelly_pct": 5.0,
        "stake_units": 2.0,
        "stake_label": "2u 💪",
        "stats": {
          "mu": 3.2,
          "sigma": 1.1,
          "L5": 3.0,
          "L10": 2.7,
          "Saison": 2.5
        },
        "last_played_date": "2026-06-11T00:30:00.000+00:00",
        "last_min": 40.0,
        "reasoning": "L5 3.0 · L10 2.7 · Saison 2.5 → attendu 3.2 · pace×0.99 · def×0.935 · H2H vs NY (série down) (n=4) : 3.0 · Domicile (n=9) : 2.9",
        "player": "Devin Vassell",
        "team": "Spurs",
        "side": "home"
      },
      {
        "prop": "PA",
        "label": "Stephon Castle moins de 22.5 pts + ast",
        "line": 22.5,
        "direction": "under",
        "confidence": 68,
        "confidence_base": 78,
        "signal_bonus": 5,
        "signal_confirm": "🆚 UNDER hit rate 3/4 vs NY",
        "signal_warning": "",
        "venue_hit": "6/9",
        "venue_hit_pct": 67,
        "h2h_hit": "3/4",
        "h2h_hit_pct": 75,
        "cote_min": 1.29,
        "real_cote": 1.97,
        "book": "draftkings",
        "books": [
          {
            "book": "draftkings",
            "cote": 1.97
          },
          {
            "book": "fanduel",
            "cote": 1.88
          },
          {
            "book": "betmgm",
            "cote": 1.85
          }
        ],
        "edge": 52.7,
        "is_real_line": true,
        "value": [
          "🎯",
          "Real DK/FD",
          "#22c55e"
        ],
        "hit_rate": "6/10",
        "hit_pct": 60,
        "hit_l10": "6/10",
        "hit_l10_pct": 60,
        "hit_l20": "8/20",
        "hit_l20_pct": 40,
        "trend": "hot",
        "trend_delta": 20.0,
        "trend_icon": "📈",
        "context": {
          "pace": 0.99,
          "vegas": 0.982,
          "def": 0.952,
          "def_rank": 26,
          "def_stat": "points"
        },
        "def_argument": "Adversaire solide vs points (#26/30)",
        "rotation_warning": null,
        "last_min_warning": null,
        "book_divergence_warning": null,
        "bounce_back": null,
        "is_series": true,
        "series_state": "down",
        "series_urgency": true,
        "h2h_avg": 21.0,
        "h2h_n": 4,
        "venue_avg": 21.6,
        "venue_n": 9,
        "venue": "domicile",
        "opp_abbr": "NY",
        "kelly_pct": 5.0,
        "stake_units": 2.0,
        "stake_label": "2u 💪",
        "stats": {
          "mu": 18.1,
          "sigma": 5.7,
          "L5": 21.2,
          "L10": 23.5,
          "Saison": 24.1
        },
        "last_played_date": "2026-06-11T00:30:00.000+00:00",
        "last_min": 26.0,
        "reasoning": "L5 21.2 · L10 23.5 · Saison 24.1 → attendu 18.1 · pace×0.99 · vegas×0.982 · def×0.952 · H2H vs NY (série down) (n=4) : 21.0 · Domicile (n=9) : 21.6",
        "player": "Stephon Castle",
        "team": "Spurs",
        "side": "home"
      },
      {
        "prop": "PR",
        "label": "Victor Wembanyama moins de 40.5 pts + reb",
        "line": 40.5,
        "direction": "under",
        "confidence": 68,
        "confidence_base": 74,
        "signal_bonus": 10,
        "signal_confirm": "📍 UNDER hit rate 8/10 à domicile · 🆚 UNDER hit rate 4/4 vs NY",
        "signal_warning": "",
        "venue_hit": "8/10",
        "venue_hit_pct": 80,
        "h2h_hit": "4/4",
        "h2h_hit_pct": 100,
        "cote_min": 1.35,
        "real_cote": 1.92,
        "book": "draftkings",
        "books": [
          {
            "book": "draftkings",
            "cote": 1.92
          },
          {
            "book": "betmgm",
            "cote": 1.8
          }
        ],
        "edge": 42.2,
        "is_real_line": true,
        "value": [
          "🎯",
          "Real DK/FD",
          "#22c55e"
        ],
        "hit_rate": "9/10",
        "hit_pct": 90,
        "hit_l10": "9/10",
        "hit_l10_pct": 90,
        "hit_l20": "16/20",
        "hit_l20_pct": 80,
        "trend": "hot",
        "trend_delta": 10.0,
        "trend_icon": "📈",
        "context": {
          "pace": 0.99,
          "vegas": 0.982,
          "def": 0.952,
          "def_rank": 26,
          "def_stat": "points"
        },
        "def_argument": "Adversaire solide vs points (#26/30)",
        "rotation_warning": null,
        "last_min_warning": null,
        "book_divergence_warning": null,
        "bounce_back": null,
        "is_series": true,
        "series_state": "down",
        "series_urgency": true,
        "h2h_avg": 38.2,
        "h2h_n": 4,
        "venue_avg": 32.9,
        "venue_n": 10,
        "venue": "domicile",
        "opp_abbr": "NY",
        "kelly_pct": 5.0,
        "stake_units": 2.0,
        "stake_label": "2u 💪",
        "stats": {
          "mu": 32.4,
          "sigma": 12.5,
          "L5": 36.4,
          "L10": 35.5,
          "Saison": 36.5
        },
        "last_played_date": "2026-06-11T00:30:00.000+00:00",
        "last_min": 44.0,
        "reasoning": "L5 36.4 · L10 35.5 · Saison 36.5 → attendu 32.4 · pace×0.99 · vegas×0.982 · def×0.952 · H2H vs NY (série down) (n=4) : 38.2 · Domicile (n=10) : 32.9",
        "player": "Victor Wembanyama",
        "team": "Spurs",
        "side": "home"
      },
      {
        "prop": "PA",
        "label": "Julian Champagnie plus de 10.5 pts + ast",
        "line": 10.5,
        "direction": "over",
        "confidence": 59,
        "confidence_base": 68,
        "signal_bonus": 0,
        "signal_confirm": "",
        "signal_warning": "",
        "venue_hit": "6/9",
        "venue_hit_pct": 67,
        "h2h_hit": "2/4",
        "h2h_hit_pct": 50,
        "cote_min": 1.46,
        "real_cote": 1.89,
        "book": "fanduel",
        "books": [
          {
            "book": "fanduel",
            "cote": 1.89
          },
          {
            "book": "betmgm",
            "cote": 1.85
          },
          {
            "book": "draftkings",
            "cote": 1.85
          }
        ],
        "edge": 29.5,
        "is_real_line": true,
        "value": [
          "🎯",
          "Real DK/FD",
          "#22c55e"
        ],
        "hit_rate": "6/10",
        "hit_pct": 60,
        "hit_l10": "6/10",
        "hit_l10_pct": 60,
        "hit_l20": "12/20",
        "hit_l20_pct": 60,
        "trend": "stable",
        "trend_delta": 0.0,
        "trend_icon": "",
        "context": {
          "pace": 0.99,
          "vegas": 0.982,
          "def": 0.952,
          "def_rank": 26,
          "def_stat": "points"
        },
        "def_argument": "Adversaire solide vs points (#26/30)",
        "rotation_warning": null,
        "last_min_warning": null,
        "book_divergence_warning": null,
        "bounce_back": null,
        "is_series": true,
        "series_state": "down",
        "series_urgency": true,
        "h2h_avg": 12.2,
        "h2h_n": 4,
        "venue_avg": 12.8,
        "venue_n": 9,
        "venue": "domicile",
        "opp_abbr": "NY",
        "kelly_pct": 5.0,
        "stake_units": 2.0,
        "stake_label": "2u 💪",
        "stats": {
          "mu": 13.0,
          "sigma": 5.2,
          "L5": 14.0,
          "L10": 13.1,
          "Saison": 12.6
        },
        "last_played_date": "2026-06-11T00:30:00.000+00:00",
        "last_min": 33.0,
        "reasoning": "L5 14.0 · L10 13.1 · Saison 12.6 → attendu 13.0 · pace×0.99 · vegas×0.982 · def×0.952 · H2H vs NY (série down) (n=4) : 12.2 · Domicile (n=9) : 12.8",
        "player": "Julian Champagnie",
        "team": "Spurs",
        "side": "home"
      },
      {
        "prop": "PRA",
        "label": "Victor Wembanyama moins de 44.5 PRA",
        "line": 44.5,
        "direction": "under",
        "confidence": 70,
        "confidence_base": 77,
        "signal_bonus": 10,
        "signal_confirm": "📍 UNDER hit rate 8/10 à domicile · 🆚 UNDER hit rate 3/4 vs NY",
        "signal_warning": "",
        "venue_hit": "8/10",
        "venue_hit_pct": 80,
        "h2h_hit": "3/4",
        "h2h_hit_pct": 75,
        "cote_min": 1.31,
        "real_cote": 1.85,
        "book": "draftkings",
        "books": [
          {
            "book": "draftkings",
            "cote": 1.85
          }
        ],
        "edge": 41.2,
        "is_real_line": true,
        "value": [
          "🎯",
          "Real DK/FD",
          "#22c55e"
        ],
        "hit_rate": "8/10",
        "hit_pct": 80,
        "hit_l10": "8/10",
        "hit_l10_pct": 80,
        "hit_l20": "15/20",
        "hit_l20_pct": 75,
        "trend": "stable",
        "trend_delta": 5.0,
        "trend_icon": "",
        "context": {
          "pace": 0.99,
          "vegas": 0.982,
          "def": 0.952,
          "def_rank": 26,
          "def_stat": "points"
        },
        "def_argument": "Adversaire solide vs points (#26/30)",
        "rotation_warning": null,
        "last_min_warning": null,
        "book_divergence_warning": null,
        "bounce_back": null,
        "is_series": true,
        "series_state": "down",
        "series_urgency": true,
        "h2h_avg": 41.0,
        "h2h_n": 4,
        "venue_avg": 35.9,
        "venue_n": 10,
        "venue": "domicile",
        "opp_abbr": "NY",
        "kelly_pct": 5.0,
        "stake_units": 2.0,
        "stake_label": "2u 💪",
        "stats": {
          "mu": 35.0,
          "sigma": 13.1,
          "L5": 39.0,
          "L10": 38.5,
          "Saison": 39.6
        },
        "last_played_date": "2026-06-11T00:30:00.000+00:00",
        "last_min": 44.0,
        "reasoning": "L5 39.0 · L10 38.5 · Saison 39.6 → attendu 35.0 · pace×0.99 · vegas×0.982 · def×0.952 · H2H vs NY (série down) (n=4) : 41.0 · Domicile (n=10) : 35.9",
        "player": "Victor Wembanyama",
        "team": "Spurs",
        "side": "home"
      }
    ],
    "away_picks": [
      {
        "prop": "PR",
        "label": "Josh Hart moins de 18.5 pts + reb",
        "line": 18.5,
        "direction": "under",
        "confidence": 76,
        "confidence_base": 79,
        "signal_bonus": 5,
        "signal_confirm": "🆚 UNDER hit rate 3/4 vs SA",
        "signal_warning": "⚠️ UNDER faible au lieu (4/9)",
        "venue_hit": "4/9",
        "venue_hit_pct": 44,
        "h2h_hit": "3/4",
        "h2h_hit_pct": 75,
        "cote_min": 1.27,
        "real_cote": 1.83,
        "book": "draftkings",
        "books": [
          {
            "book": "draftkings",
            "cote": 1.83
          }
        ],
        "edge": 44.1,
        "is_real_line": true,
        "value": [
          "🎯",
          "Real DK/FD",
          "#22c55e"
        ],
        "hit_rate": "4/10",
        "hit_pct": 40,
        "hit_l10": "4/10",
        "hit_l10_pct": 40,
        "hit_l20": "9/20",
        "hit_l20_pct": 45,
        "trend": "stable",
        "trend_delta": -5.0,
        "trend_icon": "",
        "context": {
          "pace": 0.99,
          "vegas": 0.934,
          "def": 0.965,
          "def_rank": 23,
          "def_stat": "points"
        },
        "def_argument": "Adversaire solide vs points (#23/30)",
        "rotation_warning": null,
        "last_min_warning": null,
        "book_divergence_warning": null,
        "bounce_back": null,
        "is_series": true,
        "series_state": "up",
        "series_urgency": false,
        "h2h_avg": 15.8,
        "h2h_n": 4,
        "venue_avg": 17.8,
        "venue_n": 9,
        "venue": "exterieur",
        "opp_abbr": "SA",
        "kelly_pct": 5.0,
        "stake_units": 2.0,
        "stake_label": "2u 💪",
        "stats": {
          "mu": 13.3,
          "sigma": 6.5,
          "L5": 16.0,
          "L10": 20.0,
          "Saison": 19.4
        },
        "last_played_date": "2026-06-11T00:30:00.000+00:00",
        "last_min": 33.0,
        "reasoning": "L5 16.0 · L10 20.0 · Saison 19.4 → attendu 13.3 · pace×0.99 · vegas×0.934 · def×0.965 · H2H vs SA (série up) (n=4) : 15.8 · Exterieur (n=9) : 17.8",
        "player": "Josh Hart",
        "team": "Knicks",
        "side": "away"
      },
      {
        "prop": "PTS",
        "label": "Jordan Clarkson plus de 1.5 points",
        "line": 1.5,
        "direction": "over",
        "confidence": 79,
        "confidence_base": 83,
        "signal_bonus": 5,
        "signal_confirm": "📍 OVER hit rate 6/8 à extérieur",
        "signal_warning": "",
        "venue_hit": "6/8",
        "venue_hit_pct": 75,
        "h2h_hit": "2/3",
        "h2h_hit_pct": 67,
        "cote_min": 1.21,
        "real_cote": 1.77,
        "book": "fanduel",
        "books": [
          {
            "book": "fanduel",
            "cote": 1.77
          }
        ],
        "edge": 46.3,
        "is_real_line": true,
        "value": [
          "🎯",
          "Real DK/FD",
          "#22c55e"
        ],
        "hit_rate": "8/10",
        "hit_pct": 80,
        "hit_l10": "8/10",
        "hit_l10_pct": 80,
        "hit_l20": "18/20",
        "hit_l20_pct": 90,
        "trend": "cold",
        "trend_delta": -10.0,
        "trend_icon": "📉",
        "context": {
          "pace": 0.99,
          "vegas": 0.934,
          "def": 0.965,
          "def_rank": 23,
          "def_stat": "points"
        },
        "def_argument": "Adversaire solide vs points (#23/30)",
        "rotation_warning": "Rotation reduite : 9/10 derniers matchs <15 min (derniers 5 : 5/13/6/9/3 min)",
        "last_min_warning": null,
        "book_divergence_warning": "Book quote ligne 1.5 alors qu'on estime mu=4.3 (divergence x2.89) - le bookmaker peut avoir vu un changement (rotation/blessure)",
        "bounce_back": "L3 4.0 vs saison 8.6 (-53%) → bounce back attendu",
        "is_series": true,
        "series_state": "up",
        "series_urgency": false,
        "h2h_avg": 4.0,
        "h2h_n": 3,
        "venue_avg": 4.5,
        "venue_n": 8,
        "venue": "exterieur",
        "opp_abbr": "SA",
        "kelly_pct": 5.0,
        "stake_units": 2.0,
        "stake_label": "2u 💪",
        "stats": {
          "mu": 4.3,
          "sigma": 3.0,
          "L5": 3.0,
          "L10": 3.9,
          "Saison": 8.6
        },
        "last_played_date": "2026-06-11T00:30:00.000+00:00",
        "last_min": 5.0,
        "reasoning": "L5 3.0 · L10 3.9 · Saison 8.6 → attendu 4.3 · pace×0.99 · vegas×0.934 · def×0.965 · H2H vs SA (série up) (n=3) : 4.0 · Exterieur (n=8) : 4.5",
        "player": "Jordan Clarkson",
        "team": "Knicks",
        "side": "away"
      },
      {
        "prop": "PA",
        "label": "OG Anunoby plus de 19.5 pts + ast",
        "line": 19.5,
        "direction": "over",
        "confidence": 75,
        "confidence_base": 72,
        "signal_bonus": 10,
        "signal_confirm": "📍 OVER hit rate 7/8 à extérieur · 🆚 OVER hit rate 3/4 vs SA",
        "signal_warning": "",
        "venue_hit": "7/8",
        "venue_hit_pct": 88,
        "h2h_hit": "3/4",
        "h2h_hit_pct": 75,
        "cote_min": 1.39,
        "real_cote": 1.94,
        "book": "fanduel",
        "books": [
          {
            "book": "fanduel",
            "cote": 1.94
          },
          {
            "book": "draftkings",
            "cote": 1.92
          },
          {
            "book": "betmgm",
            "cote": 1.87
          }
        ],
        "edge": 39.6,
        "is_real_line": true,
        "value": [
          "🎯",
          "Real DK/FD",
          "#22c55e"
        ],
        "hit_rate": "6/10",
        "hit_pct": 60,
        "hit_l10": "6/10",
        "hit_l10_pct": 60,
        "hit_l20": "11/20",
        "hit_l20_pct": 55,
        "trend": "stable",
        "trend_delta": 5.0,
        "trend_icon": "",
        "context": {
          "pace": 0.99,
          "vegas": 0.934,
          "def": 0.965,
          "def_rank": 23,
          "def_stat": "points"
        },
        "def_argument": "Adversaire solide vs points (#23/30)",
        "rotation_warning": null,
        "last_min_warning": null,
        "book_divergence_warning": null,
        "bounce_back": null,
        "is_series": true,
        "series_state": "up",
        "series_urgency": false,
        "h2h_avg": 25.0,
        "h2h_n": 4,
        "venue_avg": 23.8,
        "venue_n": 8,
        "venue": "exterieur",
        "opp_abbr": "SA",
        "kelly_pct": 5.0,
        "stake_units": 2.0,
        "stake_label": "2u 💪",
        "stats": {
          "mu": 23.6,
          "sigma": 6.9,
          "L5": 24.2,
          "L10": 22.3,
          "Saison": 18.9
        },
        "last_played_date": "2026-06-11T00:30:00.000+00:00",
        "last_min": 41.0,
        "reasoning": "L5 24.2 · L10 22.3 · Saison 18.9 → attendu 23.6 · pace×0.99 · vegas×0.934 · def×0.965 · H2H vs SA (série up) (n=4) : 25.0 · Exterieur (n=8) : 23.8",
        "player": "OG Anunoby",
        "team": "Knicks",
        "side": "away"
      },
      {
        "prop": "REB",
        "label": "Jalen Brunson plus de 3.5 rebonds",
        "line": 3.5,
        "direction": "over",
        "confidence": 64,
        "confidence_base": 58,
        "signal_bonus": 5,
        "signal_confirm": "🆚 OVER hit rate 3/4 vs SA",
        "signal_warning": "⚠️ OVER faible au lieu (3/9)",
        "venue_hit": "3/9",
        "venue_hit_pct": 33,
        "h2h_hit": "3/4",
        "h2h_hit_pct": 75,
        "cote_min": 1.73,
        "real_cote": 2.3,
        "book": "fanduel",
        "books": [
          {
            "book": "fanduel",
            "cote": 2.3
          },
          {
            "book": "draftkings",
            "cote": 2.25
          },
          {
            "book": "pinnacle",
            "cote": 2.24
          },
          {
            "book": "betmgm",
            "cote": 2.05
          }
        ],
        "edge": 32.9,
        "is_real_line": true,
        "value": [
          "🎯",
          "Real DK/FD",
          "#22c55e"
        ],
        "hit_rate": "6/10",
        "hit_pct": 60,
        "hit_l10": "6/10",
        "hit_l10_pct": 60,
        "hit_l20": "7/20",
        "hit_l20_pct": 35,
        "trend": "hot",
        "trend_delta": 25.0,
        "trend_icon": "📈",
        "context": {
          "pace": 0.99,
          "def": 0.973,
          "def_rank": 23,
          "def_stat": "rebonds"
        },
        "def_argument": "Adversaire solide vs rebonds (#23/30)",
        "rotation_warning": null,
        "last_min_warning": null,
        "book_divergence_warning": null,
        "bounce_back": null,
        "is_series": true,
        "series_state": "up",
        "series_urgency": false,
        "h2h_avg": 4.5,
        "h2h_n": 4,
        "venue_avg": 3.0,
        "venue_n": 9,
        "venue": "exterieur",
        "opp_abbr": "SA",
        "kelly_pct": 5.0,
        "stake_units": 2.0,
        "stake_label": "2u 💪",
        "stats": {
          "mu": 3.8,
          "sigma": 1.6,
          "L5": 4.0,
          "L10": 4.0,
          "Saison": 3.3
        },
        "last_played_date": "2026-06-11T00:30:00.000+00:00",
        "last_min": 44.0,
        "reasoning": "L5 4.0 · L10 4.0 · Saison 3.3 → attendu 3.8 · pace×0.99 · def×0.973 · H2H vs SA (série up) (n=4) : 4.5 · Exterieur (n=9) : 3.0",
        "player": "Jalen Brunson",
        "team": "Knicks",
        "side": "away"
      },
      {
        "prop": "PRA",
        "label": "Miles McBride plus de 4.5 PRA",
        "line": 4.5,
        "direction": "over",
        "confidence": 72,
        "confidence_base": 72,
        "signal_bonus": 5,
        "signal_confirm": "📍 OVER hit rate 8/9 à extérieur",
        "signal_warning": "",
        "venue_hit": "8/9",
        "venue_hit_pct": 89,
        "h2h_hit": "2/4",
        "h2h_hit_pct": 50,
        "cote_min": 1.38,
        "real_cote": 2.0,
        "book": "betmgm",
        "books": [
          {
            "book": "betmgm",
            "cote": 2.0
          },
          {
            "book": "fanduel",
            "cote": 1.96
          }
        ],
        "edge": 44.9,
        "is_real_line": true,
        "value": [
          "🎯",
          "Real DK/FD",
          "#22c55e"
        ],
        "hit_rate": "7/10",
        "hit_pct": 70,
        "hit_l10": "7/10",
        "hit_l10_pct": 70,
        "hit_l20": "14/20",
        "hit_l20_pct": 70,
        "trend": "stable",
        "trend_delta": 0.0,
        "trend_icon": "",
        "context": {
          "pace": 0.99,
          "vegas": 0.934,
          "def": 0.965,
          "def_rank": 23,
          "def_stat": "points"
        },
        "def_argument": "Adversaire solide vs points (#23/30)",
        "rotation_warning": "Rotation reduite : 4/10 derniers matchs <15 min (derniers 5 : 7/9/18/19/17 min)",
        "last_min_warning": "Dernier match 7 min (vs mediane 18 des 4 precedents) - attention au temps de jeu du match a venir",
        "book_divergence_warning": "Book quote ligne 4.5 alors qu'on estime mu=8.9 (divergence x1.97) - le bookmaker peut avoir vu un changement (rotation/blessure)",
        "bounce_back": "L3 3.0 vs saison 17.0 (-82%) → bounce back attendu",
        "is_series": true,
        "series_state": "up",
        "series_urgency": false,
        "h2h_avg": 5.0,
        "h2h_n": 4,
        "venue_avg": 11.9,
        "venue_n": 9,
        "venue": "exterieur",
        "opp_abbr": "SA",
        "kelly_pct": 5.0,
        "stake_units": 2.0,
        "stake_label": "2u 💪",
        "stats": {
          "mu": 8.9,
          "sigma": 7.3,
          "L5": 7.0,
          "L10": 8.9,
          "Saison": 17.0
        },
        "last_played_date": "2026-06-11T00:30:00.000+00:00",
        "last_min": 7.0,
        "reasoning": "L5 7.0 · L10 8.9 · Saison 17.0 → attendu 8.9 · pace×0.99 · vegas×0.934 · def×0.965 · H2H vs SA (série up) (n=4) : 5.0 · Exterieur (n=9) : 11.9",
        "player": "Miles McBride",
        "team": "Knicks",
        "side": "away"
      }
    ]
  }
}