{
  "started_at": "2026-07-16T18:08:12.048396+00:00",
  "browser_available": true,
  "camoufox_installed": true,
  "camoufox_launch_ok": false,
  "camoufox_launch_err": "CamoufoxNotInstalled: official/stable is not installed. Please run `camoufox fetch` to install.",
  "sofascore_events_by_date": {
    "2026-07-09": 21,
    "2026-07-10": 12,
    "2026-07-11": 31,
    "2026-07-12": 53,
    "2026-07-13": 58,
    "2026-07-14": 71,
    "2026-07-15": 35,
    "2026-07-16": 23
  },
  "algo_picks_total": 0,
  "algo_picks_matched": 0,
  "results_count": 0,
  "history_added": 0,
  "errors": [],
  "algo_matches_total": 0,
  "finished_at": "2026-07-16T18:08:14.175274+00:00"
}